booksread/__init__.py
booksread/booksread.py
booksread/file_convert.py
booksread/helpers.py
booksread/models.py
booksread-0.0.1.data/scripts/booksread_server.py
booksread-0.0.1.dist-info/DESCRIPTION.rst
booksread-0.0.1.dist-info/METADATA
booksread-0.0.1.dist-info/RECORD
booksread-0.0.1.dist-info/WHEEL
booksread-0.0.1.dist-info/metadata.json
booksread-0.0.1.dist-info/top_level.txt
